pyDEXP/__init__.py
pyDEXP/dexp.py
pyDEXP/unit_tests/__init__.py
pyDEXP/unit_tests/test_dexp.py
pyDEXP-1.0.0.dist-info/LICENSE.txt
pyDEXP-1.0.0.dist-info/METADATA
pyDEXP-1.0.0.dist-info/WHEEL
pyDEXP-1.0.0.dist-info/top_level.txt
pyDEXP-1.0.0.dist-info/RECORD
